py3createtorrent.py
py3createtorrent-1.2.1.dist-info/AUTHORS
py3createtorrent-1.2.1.dist-info/LICENSE.txt
py3createtorrent-1.2.1.dist-info/METADATA
py3createtorrent-1.2.1.dist-info/WHEEL
py3createtorrent-1.2.1.dist-info/entry_points.txt
py3createtorrent-1.2.1.dist-info/top_level.txt
py3createtorrent-1.2.1.dist-info/RECORD
