Metadata-Version: 2.1
Name: py3createtorrent
Version: 1.2.1
Summary: Create torrents via command line!
Home-page: https://github.com/rsnitsch/py3createtorrent
Author: Robert Nitsch
Author-email: mail@robertnitsch.de
Project-URL: Bug Reports, https://github.com/rsnitsch/py3createtorrent/issues
Project-URL: Source, https://github.com/rsnitsch/py3createtorrent
Keywords: torrents,commandline,shell,script
Classifier: Development Status :: 5 - Production/Stable
Classifier: Environment :: Console
Classifier: Intended Audience :: End Users/Desktop
Classifier: Intended Audience :: System Administrators
Classifier: Topic :: Communications :: File Sharing
Classifier: License :: OSI Approved :: GNU Lesser General Public License v3 or later (LGPLv3+)
Classifier: Programming Language :: Python :: 3
Classifier: Programming Language :: Python :: 3.5
Classifier: Programming Language :: Python :: 3.6
Classifier: Programming Language :: Python :: 3.7
Classifier: Programming Language :: Python :: 3.8
Classifier: Programming Language :: Python :: 3.9
Classifier: Programming Language :: Python :: 3.10
Classifier: Programming Language :: Python :: 3.11
Classifier: Programming Language :: Python :: 3.12
Classifier: Programming Language :: Python :: 3 :: Only
Requires-Python: >=3.5, <4
License-File: LICENSE.txt
License-File: AUTHORS
Requires-Dist: bencode.py
